{
  "entityType" : "CUSTOMER",
  "entity" : {
    "additionalInfo" : null,
    "address" : null,
    "address2" : null,
    "city" : null,
    "country" : null,
    "email" : null,
    "externalId" : {
      "entityType" : "CUSTOMER",
      "id" : "10daed90-4851-11f1-b486-a5a3f146e9be"
    },
    "id" : {
      "entityType" : "CUSTOMER",
      "id" : "10daed90-4851-11f1-b486-a5a3f146e9be"
    },
    "name" : "Customer B",
    "phone" : null,
    "state" : null,
    "title" : "Customer B",
    "zip" : null
  },
  "relations" : [ ],
  "attributes" : {
    "SERVER_SCOPE" : [ ]
  }
}