{
  "entityType" : "DEVICE",
  "entity" : {
    "additionalInfo" : {
      "lastConnectedGateway" : "46eca8e0-4b14-11f1-beb5-f5c3c85875b7"
    },
    "customerId" : {
      "entityType" : "CUSTOMER",
      "id" : "13814000-1dd2-11b2-8080-808080808080"
    },
    "deviceData" : {
      "configuration" : {
        "type" : "DEFAULT"
      },
      "transportConfiguration" : {
        "type" : "DEFAULT"
      }
    },
    "deviceProfileId" : {
      "entityType" : "DEVICE_PROFILE",
      "id" : "bd70a0a0-3b30-11f1-88fb-27c6733518bf"
    },
    "externalId" : null,
    "firmwareId" : null,
    "id" : {
      "entityType" : "DEVICE",
      "id" : "7a2f4270-4b15-11f1-beb5-f5c3c85875b7"
    },
    "label" : null,
    "name" : "b01-f10-r186-COAP",
    "softwareId" : null,
    "type" : "default"
  },
  "credentials" : {
    "credentialsId" : "1S2MLQs5X8Up8qANypO2",
    "credentialsType" : "ACCESS_TOKEN",
    "credentialsValue" : null
  },
  "relations" : [ {
    "additionalInfo" : null,
    "from" : {
      "entityType" : "DEVICE",
      "id" : "e12bd600-3c51-11f1-b8ec-93728b1a4824"
    },
    "to" : {
      "entityType" : "DEVICE",
      "id" : "7a2f4270-4b15-11f1-beb5-f5c3c85875b7"
    },
    "type" : "Created",
    "typeGroup" : "COMMON",
    "version" : 4300
  }, {
    "additionalInfo" : null,
    "from" : {
      "entityType" : "ASSET",
      "id" : "321ee870-4861-11f1-ab18-f9a04309833c"
    },
    "to" : {
      "entityType" : "DEVICE",
      "id" : "7a2f4270-4b15-11f1-beb5-f5c3c85875b7"
    },
    "type" : "Contains",
    "typeGroup" : "COMMON",
    "version" : 4503
  } ],
  "attributes" : {
    "SERVER_SCOPE" : [ {
      "booleanValue" : true,
      "doubleValue" : null,
      "jsonValue" : null,
      "key" : "active",
      "lastUpdateTs" : 1778336875542,
      "longValue" : null,
      "strValue" : null
    }, {
      "booleanValue" : null,
      "doubleValue" : null,
      "jsonValue" : null,
      "key" : "inactivityAlarmTime",
      "lastUpdateTs" : 1778336867464,
      "longValue" : 1778336867464,
      "strValue" : null
    }, {
      "booleanValue" : null,
      "doubleValue" : null,
      "jsonValue" : null,
      "key" : "lastActivityTime",
      "lastUpdateTs" : 1778347552014,
      "longValue" : 1778347551746,
      "strValue" : null
    }, {
      "booleanValue" : null,
      "doubleValue" : null,
      "jsonValue" : null,
      "key" : "lastConnectTime",
      "lastUpdateTs" : 1778347540220,
      "longValue" : 1778347540220,
      "strValue" : null
    }, {
      "booleanValue" : null,
      "doubleValue" : null,
      "jsonValue" : null,
      "key" : "lastDisconnectTime",
      "lastUpdateTs" : 1778347551749,
      "longValue" : 1778347551749,
      "strValue" : null
    } ],
    "SHARED_SCOPE" : [ ]
  },
  "calculatedFields" : [ ]
}